{
    "parentID":"3",
    "parent":"Розваги",
    "itemID":"3",
    "item":"Cпорт",

    "data":[
        {"id":"3_3_0001","lat":49.844845,"lng":24.028810,"type":"marker37","name":"спортмайданчик \"Малятко\"",
            "address":"Львів, пл. Князя Ярослава Осмомисла","img":"../app/photo/lviv/sport/Malyatko.jpg","info":"","text":"Спортивний майданчик для активних ігор малят і їх батьків на свіжому повітрі. Сприяє покращенню здоровья та фізичного стану. Обладнаний різноманітними доріжками та станками.",
            "phone":"","site":"","price":"","mon":"","tue":"","wed":"","thu":"","fri":"","sat":"","sun":"",
            "type1":"no","type2":"no","type3":"no","type4":"no","type5":"no"
        },
        {"id":"3_3_0002","lat":49.837377,"lng":24.030894,"type":"marker38","name":"Гранд клуб \"Софія\"",
            "address":"Львів, пр-т Шевченка, 10","img":"../app/photo/lviv/sport/Sofia.jpg","info":"","text":"У 1997 році був відкритий фітнес центр Гранд Клуб «Софія» – масштабний фітнес-центр, призначений для відпочинку, розваг і оздоровлення. Тепер тут діє тренажерний зал, вітамінний бар, фінська сауна, джакузі, зал аеробіки і римська баня з унікальними у Львові мармуровими лавами. Провадячи таку широку діяльність, клуб «Софія» продовжує столітні традиції славетної лазні св. Анни.",
            "phone":"+380322729000","site":"http://fitness-sofia.com/","price":"","mon":"","tue":"","wed":"","thu":"","fri":"","sat":"","sun":"",
            "type1":"no","type2":"no","type3":"no","type4":"no","type5":"no"
        },
        {"id":"3_3_0003","lat":49.826507,"lng":24.009065,"type":"marker38","name":"Скейтбординг \"Медик\"",
         "address":"Львів, вул. І. Горбачевського, 24","img":"../app/photo/lviv/sport/Skeytbordynh.jpg","info":"","text":"Скейтбординг (англ. skateboarding) — екстремальний вид спорту, що полягає в катанні, а також у виконанні різних трюків на скейтборді. Людину, яка займається скейтбордінгом, називаютьскейтбордистом або скейтером.",
         "phone":"+380322970751","site":"http://www.medic.lviv.ua/","price":"","mon":"","tue":"","wed":"","thu":"","fri":"","sat":"","sun":"",
         "type1":"no","type2":"no","type3":"no","type4":"no","type5":"no"
        },
        {"id":"3_3_0004","lat":49.842194,"lng":24.031206,"type":"marker38","name":"Скейтбординг \"Ковзанка перед Ратушою\"",
         "address":"Львів, пл. Ринок","img":"../app/photo/lviv/sport/Skeytbordynh.jpg","info":"","text":"Скейтбординг (англ. skateboarding) — екстремальний вид спорту, що полягає в катанні, а також у виконанні різних трюків на скейтборді. Людину, яка займається скейтбордінгом, називаютьскейтбордистом або скейтером.",
         "phone":"","site":"","price":"","mon":"","tue":"","wed":"","thu":"","fri":"","sat":"","sun":"",
         "type1":"no","type2":"no","type3":"no","type4":"no","type5":"no"
        },
        {"id":"3_3_0005","lat":49.690955,"lng":24.22187,"type":"marker38","name":"Скейтбординг \"Бухта Вікінгів\"",
         "address":"12 км. від Львова в напрямку Бібрки, траса Н09","img":"../app/photo/lviv/sport/Skeytbordynh.jpg","info":"","text":"Скейтбординг (англ. skateboarding) — екстремальний вид спорту, що полягає в катанні, а також у виконанні різних трюків на скейтборді. Людину, яка займається скейтбордінгом, називаютьскейтбордистом або скейтером.",
         "phone":"+380322402024","site":"http://www.viking.com.ua/","price":"","mon":"","tue":"","wed":"","thu":"","fri":"","sat":"","sun":"",
         "type1":"no","type2":"no","type3":"no","type4":"no","type5":"no"
        },
        {"id":"3_3_0006","lat":49.772991,"lng":24.009418,"type":"marker38","name":"Скейтбординг \"Кіng Cross Leopolis\"",
         "address":"Львів, вул. Стрийська, 30","img":"../app/photo/lviv/sport/Skeytbordynh.jpg","info":"","text":"Скейтбординг (англ. skateboarding) — екстремальний вид спорту, що полягає в катанні, а також у виконанні різних трюків на скейтборді. Людину, яка займається скейтбордінгом, називаютьскейтбордистом або скейтером.",
         "phone":"+380322420580","site":"http://www.kingcross.com.ua/","price":"","mon":"","tue":"","wed":"","thu":"","fri":"","sat":"","sun":"",
         "type1":"no","type2":"no","type3":"no","type4":"no","type5":"no"
        },
        {"id":"3_3_0007","lat":49.691031,"lng":24.222749,"type":"marker38","name":"Пейнтбольний клуб \"Бухта Вікінгів\"",
         "address":"12 км. від Львова в напрямку Бібрки, траса Н09","img":"../app/photo/lviv/sport/Peyntbol.jpg","info":"","text":"Пейнтбол (англ. Paintball — кулька з фарбою) — командна гра з застосуванням ручної пневматичної зброї (маркерів), яка стріляє капсулами з фарбою, що розбиваються при ударі по мішені, фарбуючи її. Існують два різновиди пейнтболу: спортивний пейнтбол та тактичний пейнтбол. За своєю манерою гра імітує швидкоплинні вогневі контакти на обмеженому просторі. Ігри проводяться на лісових або відкритих полях, у приміщеннях, із природними або штучними перешкодами й укриттями. Розрізняють пейнтбол як вид відпочинку — для всіх охочих; як спосіб тренування — для охоронців, поліцейських або спецназу; і як спорт — для турнірних команд (Вікіпедія).",
         "phone":"+380322402024","site":"http://www.viking.com.ua/","price":"","mon":"","tue":"","wed":"","thu":"","fri":"","sat":"","sun":"",
         "type1":"no","type2":"no","type3":"no","type4":"no","type5":"no"
        },
        {"id":"3_3_0008","lat":49.825255,"lng":24.004142,"type":"marker38","name":"Пейнтбольний клуб \"Камікадзе\"",
         "address":"Львів, вул. Прородня, 10","img":"../app/photo/lviv/sport/Peyntbol Kamikadze.jpg","info":"","text":"Пейнтбол клуб КАМІКАДЗЕ Львів був створений в 2008 році для того, щоб популяризувати пейнтбол у Львові та за його межами, об'єднати поціновувачів цього виду спорту і відпочинку. Наш клуб є членом \"Асоціації пейнтбольних клубів\" (www.pbclubs.in.ua), яка об'єднує десятки пейнтбольних клубів по всій Україні. На базі клубу з 2010 року тренується Тактична Пейнтбольна Команда \"Mercenaries\" ( Найманці ), члени якої постійно беруть участь в різноманітних пейнтбольних тактичних турнірах та Великих Пейнтбольних Маневрах в різних містах України (Львів, Чернівці, Івано-Франківськ, Харків тощо).",
         "phone":"+380932443434","site":"http://www.kamikadze.lviv.ua/","price":"","mon":"","tue":"","wed":"","thu":"","fri":"","sat":"","sun":"",
         "type1":"no","type2":"no","type3":"no","type4":"no","type5":"no"
        },
        {"id":"3_3_0009","lat":49.83183,"lng":23.970221,"type":"marker38","name":"Пейнтбольний клуб \"Paintball shop.ua\"",
         "address":"Львів, вул. Городоцька, 172 (офіс 401)","img":"../app/photo/lviv/sport/Peyntbol paintball.jpg","info":"","text":"Пейнтбол (англ. Paintball — кулька з фарбою) — командна гра з застосуванням ручної пневматичної зброї (маркерів), яка стріляє капсулами з фарбою, що розбиваються при ударі по мішені, фарбуючи її. Існують два різновиди пейнтболу: спортивний пейнтбол та тактичний пейнтбол. За своєю манерою гра імітує швидкоплинні вогневі контакти на обмеженому просторі. Ігри проводяться на лісових або відкритих полях, у приміщеннях, із природними або штучними перешкодами й укриттями. Розрізняють пейнтбол як вид відпочинку — для всіх охочих; як спосіб тренування — для охоронців, поліцейських або спецназу; і як спорт — для турнірних команд (Вікіпедія).",
         "phone":"+380322451515","site":"http://www.paintball.lviv.ua/","price":"","mon":"","tue":"","wed":"","thu":"","fri":"","sat":"","sun":"",
         "type1":"no","type2":"no","type3":"no","type4":"no","type5":"no"
        },
        {"id":"3_3_0010","lat":49.828148,"lng":24.009968,"type":"marker38","name":"Пейнтбольний клуб \"Extreme ball\"",
         "address":"Львів, вул. Івана Горбачевського, 24","img":"../app/photo/lviv/sport/Peyntbol Extreme ball.jpg","info":"","text":"Пейнтбольний клуб eXtreme ball (Paintball club eXtreme ball) заснований для активного розвитку пейнтболу (від англ. - paintball), для популяризації цього виду спорту та відпочинку. Пейнтбольний клуб eXtreme ball пропонує якісний, індивідуальний підхід до кожного клієнта. Кожен наш клієнт може замовити гру за власним сценарієм, на свому майданчику. Львів, Львівська область чи Західна Україна - ми не обмежуємось територією проведення ігор.",
         "phone":"+380667722221","site":"","price":"","mon":"","tue":"","wed":"","thu":"","fri":"","sat":"","sun":"",
         "type1":"no","type2":"no","type3":"no","type4":"no","type5":"no"
        },
        {"id":"3_3_0011","lat":49.778662,"lng":24.018695,"type":"marker38","name":"Пейнтбольний клуб \"Дельта\"",
         "address":"Львів, вул. Стрийська, 179","img":"../app/photo/lviv/sport/Peyntbol Delta.jpg","info":"","text":"Пейнтбол (англ. Paintball — кулька з фарбою) — командна гра з застосуванням ручної пневматичної зброї (маркерів), яка стріляє капсулами з фарбою, що розбиваються при ударі по мішені, фарбуючи її. Існують два різновиди пейнтболу: спортивний пейнтбол та тактичний пейнтбол. За своєю манерою гра імітує швидкоплинні вогневі контакти на обмеженому просторі. Ігри проводяться на лісових або відкритих полях, у приміщеннях, із природними або штучними перешкодами й укриттями. Розрізняють пейнтбол як вид відпочинку — для всіх охочих; як спосіб тренування — для охоронців, поліцейських або спецназу; і як спорт — для турнірних команд (Вікіпедія).",
         "phone":"+380674184304","site":"http://deltaclub.lviv.ua/","price":"","mon":"","tue":"","wed":"","thu":"","fri":"","sat":"","sun":"",
         "type1":"no","type2":"no","type3":"no","type4":"no","type5":"no"
        },
        {"id":"3_3_0012","lat":49.833923,"lng":24.012778,"type":"marker38","name":"Пейнтбольний клуб \"Чорногора\"",
         "address":"Львів, вул. Глибока, 10","img":"../app/photo/lviv/sport/Peyntbol Chornohora.jpg","info":"","text":"Пейнтбольний клуб Чорногора — заснований захопленими пейнтболом людьми. В один момент ця гра стала для нас однією з найцікавіших розваг. Нашим завданням, є допомогти доторкнутися до чар пейнтболу вам. Якщо ви спробуєте хоча б раз, то обов”язково до нас повернетеся. Пейнтбол на диво не агресивна гра, не зважаючи на наявність в ній зброї – маркерів. Навпаки, гра супроводжується взаємодопомогою, усмішками і позитивними емоціями. Чорногора — це глобальний бренд який популяризує активний відпочинок. Якщо ви любите велосипед, ми вам запропонуємо велосипеди, якщо зібралися в гори, то у нас знайдете лижі а якщо ви турист, то — найкраще туристичне спорядження, а якщо в горах ви себе почуваєте не впевнено, то ми маємо для вас найкраших провідників та карпатських гідів. Але завданням пейнтбольного клубу є пейнтбол. Ми пропонуємо вам оренду спорядження та спеціальних майданчиків у Львові та Ужгороді, також можна замовити спорядження на виїзд за межі міст. Вперед за новими враженнями.",
         "phone":"+380322385740","site":"","price":"","mon":"","tue":"","wed":"","thu":"","fri":"","sat":"","sun":"",
         "type1":"no","type2":"no","type3":"no","type4":"no","type5":"no"
        },
        {"id":"3_3_0013","lat":49.796004,"lng":24.075315,"type":"marker38","name":"Пейнтбольний клуб \"PSIHOV GROUP\"",
         "address":"Львів, вул. Надійна, 6а","img":"../app/photo/lviv/sport/Peyntbol PSIHOV GROUP.jpg","info":"","text":"Пейнтбол (англ. Paintball — кулька з фарбою) — командна гра з застосуванням ручної пневматичної зброї (маркерів), яка стріляє капсулами з фарбою, що розбиваються при ударі по мішені, фарбуючи її. Існують два різновиди пейнтболу: спортивний пейнтбол та тактичний пейнтбол. За своєю манерою гра імітує швидкоплинні вогневі контакти на обмеженому просторі. Ігри проводяться на лісових або відкритих полях, у приміщеннях, із природними або штучними перешкодами й укриттями. Розрізняють пейнтбол як вид відпочинку — для всіх охочих; як спосіб тренування — для охоронців, поліцейських або спецназу; і як спорт — для турнірних команд (Вікіпедія).",
         "phone":"+380673006118","site":"http://strike.psihov.net.ua/","price":"","mon":"","tue":"","wed":"","thu":"","fri":"","sat":"","sun":"",
         "type1":"no","type2":"no","type3":"no","type4":"no","type5":"no"
        },
        {"id":"3_3_0014","lat":49.856053,"lng":24.027956,"type":"marker38","name":"Пейнтбольний клуб \"Ангар Б-3\"",
         "address":"Львів, вул. Замарстинівська, 53","img":"../app/photo/lviv/sport/Peyntbol B3.jpg","info":"","text":"Пейнтбол (англ. Paintball — кулька з фарбою) — командна гра з застосуванням ручної пневматичної зброї (маркерів), яка стріляє капсулами з фарбою, що розбиваються при ударі по мішені, фарбуючи її. Існують два різновиди пейнтболу: спортивний пейнтбол та тактичний пейнтбол. За своєю манерою гра імітує швидкоплинні вогневі контакти на обмеженому просторі. Ігри проводяться на лісових або відкритих полях, у приміщеннях, із природними або штучними перешкодами й укриттями. Розрізняють пейнтбол як вид відпочинку — для всіх охочих; як спосіб тренування — для охоронців, поліцейських або спецназу; і як спорт — для турнірних команд (Вікіпедія).",
         "phone":"+380677847190","site":"http://b3.lviv.ua/","price":"","mon":"","tue":"","wed":"","thu":"","fri":"","sat":"","sun":"",
         "type1":"no","type2":"no","type3":"no","type4":"no","type5":"no"
        },
        {"id":"3_3_0015","lat":49.83503,"lng":24.005596,"type":"marker38","name":"Клуб активного відпочинку \"Адреналін\"",
         "address":"Львів, вул. Степана Бандери, 83","img":"../app/photo/lviv/sport/KAVA.jpg","info":"","text":"Клуб Активного Відпочинку Адреналін (KAVA) для тих, хто любить екстрім, активний відпочинок на природі, подорожі та яскраве життя. НЕ БУДЬ ПАСИВНИМ В ЦЬОМУ ЖИТТІ...",
         "phone":"+380677847190","site":"http://kava.ua/","price":"","mon":"","tue":"","wed":"","thu":"","fri":"","sat":"","sun":"",
         "type1":"no","type2":"no","type3":"no","type4":"no","type5":"no"
        },
        {"id":"3_3_0016","lat":49.852704,"lng":24.013654,"type":"marker38","name":"Стадіон \"СКА\"",
         "address":"Львів, вул. Клепарівська, 39а","img":"../app/photo/lviv/sport/Stadion SKA.jpg","info":"","text":"багатофункціональний стадіон у Львові. Входить до складу Навчально-спортивної бази літніх видів спорту Міністерства оборони України (Львів). Збудований у 1950-х роках. Домашня арена львівського спідвейного клубу «СКА-Фаворит».На стадіоні проведено фінал юніорського чемпіонату світу 1990 року, півфінал особистого чемпіонату Європи 2001 і 2003, фінал особистого чемпіонату Європи зі спідвею у 2008 і 2009 роках. Довжина треку: 382 м, рекорд: 67,07 сек, його встановив Діан Стендінг (Англія) 9 вересня 1990 року. Третій після «Арени Львів» та «України» найбільший футбольний стадіон Львова. Тут виступали львівські футбольні команди «Карпати», СКА і «Львів». Зараз на СКА свої домашні ігри проводить молодіжна команда «Карпат».",
         "phone":"+380322332379","site":"","price":"","mon":"","tue":"","wed":"","thu":"","fri":"","sat":"","sun":"",
         "type1":"no","type2":"no","type3":"no","type4":"no","type5":"no"
        },
        {"id":"3_3_0017","lat":49.834987,"lng":24.061102,"type":"marker38","name":"Стадіон \"Скіф\"",
         "address":"Львів, вул. Черемшини, 17","img":"../app/photo/lviv/sport/SKIF.jpg","info":"","text":"Комплексно-спортивна база Львівського державного університету фізичної культури «Скіф» — спортивна база у Львові. Найстаріший серед сучасних стадіонів Львова, споруджений 1897 року. Розташована на вул. Черемшини, 17, межує з Личаківським парком. Землю під стадіон для гімнастичного товариства «Сокіл» міська влада виділила 1895 року. Спортивний комплекс споруджено під Личаківським парком 1897 року — футбольне поле стандартних розмірів із біговими доріжками довкола та трибунами для глядачів, критий кінний манеж, зали для занять гімнастикою та фехтуванням. Автори проекту; Іван Левинський та Е. Ковач. Трибуни були розраховані на 30 тисяч глядачів. 1898 року за проектом Левинського збудовано службове приміщення в закопанському стилі. (Вікіпедія)",
         "phone":"+380322768985","site":"","price":"","mon":"","tue":"","wed":"","thu":"","fri":"","sat":"","sun":"",
         "type1":"no","type2":"no","type3":"no","type4":"no","type5":"no"
        },
        {"id":"3_3_0018","lat":49.819339,"lng":24.048126,"type":"marker38","name":"Стадіон \"Україна\"",
         "address":"Львів, вул. Липова Алея, 5","img":"../app/photo/lviv/sport/Stadion Ukraine.jpg","info":"","text":"«Україна» — багатофункціональний стадіон у Львові. Відкритий 1963 року. За радянських часів називався «Дружба». Домашній стадіон молодіжної команди футбольного клубу «Карпати» (Львів). Розташований недалеко від центральної частини міста, у Снопківському парку, пам'ятці садово-паркового мистецтва.",
         "phone":"+380322705030","site":"","price":"","mon":"","tue":"","wed":"","thu":"","fri":"","sat":"","sun":"",
         "type1":"no","type2":"no","type3":"no","type4":"no","type5":"no"
        },
        {"id":"3_3_0019","lat":49.830119,"lng":24.053518,"type":"marker38","name":"Стадіон \"Юний Школяр\"",
         "address":"Львів, вул. Анатолія Вахнянина, 1","img":"../app/photo/lviv/sport/Stadion Yunyy Shkolyar.jpg","info":"","text":"Стадіон розташований в межах лісопарку “Погулянка” під схилом Личаківського цвинтаря. Складається з трьох футбольних полів – основного та двох тренувальних. Основне поле має трав’яний настил, оточене трав’яними доріжками, з південного боку влаштовані глядацькі трибуни. У західній частині стадіону розташована адміністративна споруда.",
         "phone":"+380322752365","site":"","price":"","mon":"","tue":"","wed":"","thu":"","fri":"","sat":"","sun":"",
         "type1":"no","type2":"no","type3":"no","type4":"no","type5":"no"
        },
        {"id":"3_3_0020","lat":49.857272,"lng":24.027314,"type":"marker38","name":"Настільний теніс \"Дозвілля\"",
         "address":"Львів, вул. Замарстинівська, 71","img":"../app/photo/lviv/sport/Tennis Dozvillya.jpg","info":"","text":"Настільний теніс (пінг-понг) — один із найпопулярніших видів спорту у світі. Гра полягає в перекиданні м'яча ракетками так, щоб він ударявся певним чином об ігровий стіл на стороні суперника.",
         "phone":"+380322590362","site":"","price":"","mon":"","tue":"","wed":"","thu":"","fri":"","sat":"","sun":"",
         "type1":"no","type2":"no","type3":"no","type4":"no","type5":"no"
        },
        {"id":"3_3_0021","lat":49.811965,"lng":24.012938,"type":"marker38","name":"Тенісні корти \"Динамо\"",
         "address":"Львів, вул. В.Янева, 10","img":"../app/photo/lviv/sport/Dynamo.jpg","info":"","text":"Спортивний комплекс олімпійської підготовки «Динамо» - 15 тенісних кортів (тенісит власного виготовлення)",
         "phone":"+380322632420","site":"http://dynamo-lviv.com/","price":"","mon":"","tue":"","wed":"","thu":"","fri":"","sat":"","sun":"",
         "type1":"no","type2":"no","type3":"no","type4":"no","type5":"no"
        },
        {"id":"3_3_0022","lat":49.831668,"lng":24.036187,"type":"marker38","name":"Тенісні корти \"Євроспорт\"",
         "address":"Львів, пл. Петрушевича, 1","img":"../app/photo/lviv/sport/Tennis eurosport.jpg","info":"","text":"Загалом \"Євроспорт\" має сім ґрунтових кортів. Із них три закриті, що забезпечує можливість тренувань цілий рік. Саме це дає нам можливість проводити та приймати на базі тенісного клубу змагання як Всеукраїнського, так і Міжнародного рівнів. У Клубі діють дитячі секції, проводяться персональні заняття для дітей та дорослих.",
         "phone":"+380322763327","site":"http://www.eurosport.lviv.ua/","price":"","mon":"","tue":"","wed":"","thu":"","fri":"","sat":"","sun":"",
         "type1":"no","type2":"no","type3":"no","type4":"no","type5":"no"
        },
        {"id":"3_3_0023","lat":49.82971,"lng":24.004981,"type":"marker38","name":"Тенісні корти \"ПС Україна\"",
         "address":"Львів, вул. Мельника, 18","img":"../app/photo/lviv/sport/Tennis Ukraine.jpg","info":"","text":"Відкриті грунтові корти. Проводяться заняття лише з дітьми. Вартість: близько 100 грн./міс., але все залежить від конкретного тренера і кількості занять. Час роботи: 8.00-20.00. Також на тенісних кортах проводять різні турніри серед дітей, юніорів і дорослих. Індивідуальні заняття дорослих лише в разі особистої домовленості з тренером.",
         "phone":"+380322377321","site":"","price":"","mon":"","tue":"","wed":"","thu":"","fri":"","sat":"","sun":"",
         "type1":"no","type2":"no","type3":"no","type4":"no","type5":"no"
        },
        {"id":"3_3_0024","lat":49.833480,"lng":24.023148,"type":"marker38","name":"Тенісні корти \"Майстер\"",
         "address":"Львів, вул. Колеси, 8","img":"../app/photo/lviv/sport/Tennis Master.jpg","info":"","text":"Тому запрошуємо гостей готелю, львів’ян і просто любителів цього красивого спорту випробувати відмінне хардове покриття корту, тенісну стінку.",
         "phone":"+380322721940","site":"","price":"","mon":"","tue":"","wed":"","thu":"","fri":"","sat":"","sun":"",
         "type1":"no","type2":"no","type3":"no","type4":"no","type5":"no"
        },
        {"id":"3_3_0025","lat":49.842113,"lng":24.019303,"type":"marker38","name":"Тенісні корти \"Орієнтир\"",
         "address":"Львів, вул. Огієнка, 18","img":"../app/photo/lviv/sport/Tennis.jpg","info":"","text":"Те́ніс (англ. tennis) або вели́кий те́ніс — вид спорту, у якому грає двоє гравців один проти одного, або дві команди по два гравці в кожній, команда проти команди, на майданчику — корті, поділеному навпіл поперечною сіткою.",
         "phone":"+380322721940","site":"","price":"","mon":"","tue":"","wed":"","thu":"","fri":"","sat":"","sun":"",
         "type1":"no","type2":"no","type3":"no","type4":"no","type5":"no"
        },
        {"id":"3_3_0026","lat":49.819526,"lng":23.982917,"type":"marker38","name":"Тенісні корти \"Пілот\"",
         "address":"Львів, вул. Петлюри, 39","img":"../app/photo/lviv/sport/Tennis.jpg","info":"","text":"Те́ніс (англ. tennis) або вели́кий те́ніс — вид спорту, у якому грає двоє гравців один проти одного, або дві команди по два гравці в кожній, команда проти команди, на майданчику — корті, поділеному навпіл поперечною сіткою.",
         "phone":"+380322629052","site":"","price":"","mon":"","tue":"","wed":"","thu":"","fri":"","sat":"","sun":"",
         "type1":"no","type2":"no","type3":"no","type4":"no","type5":"no"
        },
        {"id":"3_3_0027","lat":49.830080,"lng":24.054552,"type":"marker38","name":"Фрізбі клуб \"Wild West\"",
         "address":"Львів, вул. Вахнянина, 1","img":"../app/photo/lviv/sport/frisbee.jpg","info":"","text":"Львівський алтимат-клуб. Алтимат - це командний вид спорту з фризбі (літаючою тарілкою). Запрошуємо на тренування всіх, хто хотів би спробувати себе в цьому виді спорту, незалежно від віку, статі та вміння \"кидати тарілку\".",
         "phone":"+380632873079","site":"http://frisbee.lviv.ua/","price":"","mon":"","tue":"","wed":"","thu":"","fri":"","sat":"","sun":"",
         "type1":"no","type2":"no","type3":"no","type4":"no","type5":"no"
        },
        {"id":"3_3_0028","lat":49.82685,"lng":24.00885,"type":"marker38","name":"Тенісні корти \"Медик\"",
         "address":"Львів, вул. Горбачевського, 24","img":"../app/photo/lviv/sport/Medyk.jpg","info":"","text":"Спортивно-розважальний комплекс «Медик» у Львові, розташований у мальовничій парковій зоні на околиці центру — це чудове місце для проведення сімейного відпочинку чи у дружній компанії.",
         "phone":"+380322970751","site":"http://medic.lviv.ua/big-tennis","price":"","mon":"","tue":"","wed":"","thu":"","fri":"","sat":"","sun":"",
         "type1":"no","type2":"no","type3":"no","type4":"no","type5":"no"
        },
        {"id":"3_3_0029","lat":49.827333,"lng":24.037933,"type":"marker38","name":"Тенісні корти \"Срібна ракетка\"",
         "address":"Львів, вул. Тютюнників, 49","img":"../app/photo/lviv/sport/Sribna Raketke.jpg","info":"","text":"Те́ніс (англ. tennis) або вели́кий те́ніс — вид спорту, у якому грає двоє гравців один проти одного, або дві команди по два гравці в кожній, команда проти команди, на майданчику — корті, поділеному навпіл поперечною сіткою.",
         "phone":"+380322721940","site":"","price":"","mon":"","tue":"","wed":"","thu":"","fri":"","sat":"","sun":"",
         "type1":"no","type2":"no","type3":"no","type4":"no","type5":"no"
        },
        {"id":"3_3_0030","lat":49.8315100,"lng":24.0429170,"type":"marker38","name":"Тенісні корти \"Динамо\"",
         "address":"Львів, вул. Зелена, 59 (В.Янева, 10)","img":"../app/photo/lviv/sport/Dynamo.jpg","info":"","text":"Кількість відкритих кортів - 15. Покриття - відкритий грунт. 2 закритих тенісних корти з покриттям Терафлекс. Час роботи: 7.00-22.00. Вартість оренди корту: 50 грн./година. Прокат м'ячів, ракеток - 10 грн. Для занять з тренером необхідно заздалегідь домовитися.",
         "phone":"+380322754234","site":"http://dynamo-lviv.com","price":"","mon":"","tue":"","wed":"","thu":"","fri":"","sat":"","sun":"",
         "type1":"no","type2":"no","type3":"no","type4":"no","type5":"no"
        },
        {"id":"3_3_0031","lat":49.691648,"lng": 24.225147,"type":"marker38","name":"База відпочинку \"Бухта Вікінгів\"",
         "address":"12 км. від Львова в напрямку Бібрки, траса Н09","img":"../app/photo/lviv/sport/Buhta Vikongiv.jpg","info":"","text":"Катамарани,мангали,тенісні корти,поля для футболу, бескетболу та волейболу, дитячі майданчики,російська баня, велосипеди та веломобілі на прокат,Верхова їзда, катання в бричці,риболовля",
         "phone":"+380322403428","site":"http://www.viking.com.ua/","price":"","mon":"","tue":"","wed":"","thu":"","fri":"","sat":"","sun":"",
         "type1":"no","type2":"no","type3":"no","type4":"no","type5":"no"
        },
        {"id":"3_3_0032","lat":49.828269,"lng":23.991319,"type":"marker38","name":"Настільний теніс \"Малі\"",
         "address":"Львів, вул. Героїа УПА, 77","img":"../app/photo/lviv/sport/Tenis Mali.jpg","info":"","text":"Настільний теніс (пінг-понг) — один із найпопулярніших видів спорту у світі. Гра полягає в перекиданні м'яча ракетками так, щоб він ударявся певним чином об ігровий стіл на стороні суперника.",
         "phone":"+380322393101","site":"http://mali.lviv.ua/","price":"","mon":"","tue":"","wed":"","thu":"","fri":"","sat":"","sun":"",
         "type1":"no","type2":"no","type3":"no","type4":"no","type5":"no"
        },
        {"id":"3_3_0033","lat":49.813230,"lng":24.055579,"type":"marker38","name":"Спортивно розважальний комплекс \"Апекс\"",
         "address":"Львів, вул. Бузкова, 2","img":"../app/photo/lviv/sport/Apex.jpg","info":"","text":"Відпочинок для всієї родини. На Вас чекають: картинг, тир,роллердром,настільний футбол,тир,лазерні бої,джампінг,скейт",
         "phone":"+380322453706","site":"http://apex.lviv.ua/","price":"","mon":"","tue":"","wed":"","thu":"","fri":"","sat":"","sun":"",
         "type1":"no","type2":"no","type3":"no","type4":"no","type5":"no"
        },
        {"id":"3_3_0034","lat":49.831402,"lng":24.046069,"type":"marker38","name":"Стрибки з парашутом \"Екстремальний відпочинок\"",
         "address":"Львів, вул. Левицького, 84","img":"../app/photo/lviv/sport/Parashut.jpg","info":"","text":"Стрибки з парашутом – незвичайний активний відпочинок і екстремальний спорт. Перший стрибок з парашутом – це можливість відчути упевненість у своїх силах і довести оточенню свою сміливість. Адже стрибнути з парашутом здатний не кожен з нас! Парашутизм як ектремальний відпочинок – справжня знахідка для екстремалів. Ті любителі екстремального відпочинку, у кого відчуття від стрибків з парашутом вже притупилися, можуть спробувати такі різновиди парашутного спорту, як стрибки з малих висот, бриючий політ над землею, стрибки з повітряних куль і вертольотів і інший активний відпочинок для екстремалів.",
         "phone":"+380322750591","site":"","price":"","mon":"","tue":"","wed":"","thu":"","fri":"","sat":"","sun":"",
         "type1":"no","type2":"no","type3":"no","type4":"no","type5":"no"
        },
        {"id":"3_3_0035","lat":49.843055,"lng":24.035383,"type":"marker38","name":"Скейт майданчик",
         "address":"Львів, вул. Винниченка, порохова вежа","img":"../app/photo/lviv/sport/Skait.jpg","info":"","text":"спеціально збудований майданчик для людей, що займаються екстремальними видами спорту, такими як скейтборд, стрітборд, агресив-ролики, велосипеди ВМХ, самокат, щоб кататися і вдосконалювати трюки. Скейт-парк може містити такі фігури, як рампи (half pipes), розгінки (quarter pipes), поручні (hand rails), фанбокси (trick boxes), піраміди (pyramids), сходинки (stairs) та інші фігури для виконання трюків.",
         "phone":"","site":"","price":"","mon":"","tue":"","wed":"","thu":"","fri":"","sat":"","sun":"",
         "type1":"no","type2":"no","type3":"no","type4":"no","type5":"no"
        },
        {"id":"3_3_0036","lat":49.806058,"lng":23.997788,"type":"marker38","name":"Дайвінг та підводне полювання",
         "address":"Львів, вул. Княгині Ольги, 114","img":"../app/photo/lviv/sport/diving.jpg","info":"","text":"Дайвінґ (англ. Scuba diving) або Пірнання — одна з форм підводного плавання, в якому пірнальник (дайвер) використовує певні технічні засоби для дихання під водою. Хоча, чисто технічно, дайвінґ означає будь-яке перебування під водою, як правило, мова йде про рекреаційний скуба дайвінґ (recreational scuba diving), тобто розважальне пірнання з апаратом підводного дихання. Термін SCUBA є англійською абрівіатурою і означає Self Contained Underwater Breathing Apparatus (самостійний апарат підводного дихання), акваланг. Родоначальником пірнання з апаратом підводного дихання є усім відомий Жак-Ів Кусто. Саме він створив в 1943 році акваланг, відкривши двері у прекрасний підводний світ мільйонам людей.",
         "phone":"+380679969579","site":"","price":"","mon":"","tue":"","wed":"","thu":"","fri":"","sat":"","sun":"",
         "type1":"no","type2":"no","type3":"no","type4":"no","type5":"no"
        },
        {"id":"3_3_0037","lat":49.830886,"lng":24.033719,"type":"marker38","name":"Дайвінг та підводне полювання",
         "address":"Львів, вул. Шота Руставелі, 30","img":"../app/photo/lviv/sport/diving.jpg","info":"","text":"Дайвінґ (англ. Scuba diving) або Пірнання — одна з форм підводного плавання, в якому пірнальник (дайвер) використовує певні технічні засоби для дихання під водою. Хоча, чисто технічно, дайвінґ означає будь-яке перебування під водою, як правило, мова йде про рекреаційний скуба дайвінґ (recreational scuba diving), тобто розважальне пірнання з апаратом підводного дихання. Термін SCUBA є англійською абрівіатурою і означає Self Contained Underwater Breathing Apparatus (самостійний апарат підводного дихання), акваланг. Родоначальником пірнання з апаратом підводного дихання є усім відомий Жак-Ів Кусто. Саме він створив в 1943 році акваланг, відкривши двері у прекрасний підводний світ мільйонам людей.",
         "phone":"+380322754981","site":"","price":"","mon":"","tue":"","wed":"","thu":"","fri":"","sat":"","sun":"",
         "type1":"no","type2":"no","type3":"no","type4":"no","type5":"no"
        },
        {"id":"3_3_0038","lat":49.835600,"lng":23.996173,"type":"marker38","name":"Спортивно-оздоровчий комплекс \"Інтерспорт\"",
         "address":"Львів, вул. Городоцька, 174","img":"../app/photo/lviv/sport/InterSport.jpg","info":"","text":"",
         "phone":"+380322451750","site":"http://intersport.lviv.ua/","price":"","mon":"","tue":"","wed":"","thu":"","fri":"","sat":"","sun":"",
         "type1":"no","type2":"no","type3":"no","type4":"no","type5":"no"
        },
        {"id":"3_3_0039","lat":49.821496,"lng":24.013116,"type":"marker38","name":"Спортивно-оздоровчий комплекс \"Інтерспорт\"",
         "address":"Львів, вул. Бойківська, 5","img":"../app/photo/lviv/sport/InterSport.jpg","info":"","text":"",
         "phone":"+380322379988","site":"http://intersport.lviv.ua/","price":"","mon":"","tue":"","wed":"","thu":"","fri":"","sat":"","sun":"",
         "type1":"no","type2":"no","type3":"no","type4":"no","type5":"no"
        },
        {"id":"3_3_0040","lat":49.451337,"lng":24.043297,"type":"marker38","name":"Стрибки з парашутом \"Скай – Груп\"",
         "address":"40км. на південь від м.Львова (Крупське)","img":"../app/photo/lviv/sport/sky group.jpg","info":"","text":"Західне авіаційне товариство „СКАЙ – ГРУП” створене з метою розвитку авіаційних видів спорту. Ми - команда однодумців, яка проводить набір і підготовку бажаючих “перевірити себе небом”, здійснює організацію та проведення стрибків з парашутом на території Західної України, популяризує їх серед молоді. Проводимо підготовку молодого поповнення для Збройних Сил України, спортсменів-парашутистів для участі у змаганнях різних рівнів, виховуємо у молоді почуття патріотизму та любові до Батьківщини. Ми проводимо свою діяльність і прикладаємо зусилля для досягнення світлої і благородної мети: об’єднання і збільшення людей, для яких НЕБО – це сенс життя.Західне авіаційне товариство „СКАЙ – ГРУП” створене з метою розвитку авіаційних видів спорту. Ми - команда однодумців, яка проводить набір і підготовку бажаючих “перевірити себе небом”, здійснює організацію та проведення стрибків з парашутом на території Західної України, популяризує їх серед молоді. Проводимо підготовку молодого поповнення для Збройних Сил України, спортсменів-парашутистів для участі у змаганнях різних рівнів, виховуємо у молоді почуття патріотизму та любові до Батьківщини. Ми проводимо свою діяльність і прикладаємо зусилля для досягнення світлої і благородної мети: об’єднання і збільшення людей, для яких НЕБО – це сенс життя.",
         "phone":"+380675887278","site":"http://sky-group.org.ua/","price":"","mon":"","tue":"","wed":"","thu":"","fri":"","sat":"","sun":"",
         "type1":"no","type2":"no","type3":"no","type4":"no","type5":"no"
        },
        {"id":"3_3_0041","lat":49.795394,"lng":24.058996,"type":"marker38","name":"Мережа фітнес клубів \"Sport Life\"",
         "address":"Львів, вул. Зубрівська, 38","img":"../app/photo/lviv/sport/Sport Life Syhiv.jpg","info":"","text":"20 березня 2013 року відкрився другий фітнес клуб Sport Life у Львові. Новий клуб розміщений на двох поверхах окремої споруди. За бездоганною якістю та кількістю представлених фітнес послуг в місті йому немає рівних.Мережа «Спорт Лайф» на сьогоднішній день є найбільшою і динамічно зростаючої мережею фітнес клубів в Україні. Головною особливістю і перевагою в принципі роботи мережі є те, що ми пропонуємо найширший спектр фітнес напрямків і послуг, що надається за єдиною мережевою клубною карткою під керівництвом кращих спортивних тренерів. А Клуби мережі «Спорт Лайф» територіально розташовані таким чином, що клієнт завжди може вибирати для відвідування той клуб, який знаходиться ближче до місця його роботи або проживання. При цьому клієнт мережі завжди може отримувати різні унікальні послуги, що надаються тільки в якомусь конкретному клубі, і, при цьому, мати можливість в будь-який час відвідувати кілька або всі клуби мережі!",
         "phone":"+380322327181","site":"http://www.sportlife.ua/","price":"","mon":"","tue":"","wed":"","thu":"","fri":"","sat":"","sun":"",
         "type1":"no","type2":"no","type3":"no","type4":"no","type5":"no"
        },
        {"id":"3_3_0042","lat":49.831843,"lng":23.997460,"type":"marker38","name":"Мережа фітнес клубів \"Sport Life\"",
         "address":"Львів, вул. Героїв УПА, 72, корпус 40","img":"../app/photo/lviv/sport/Sport Life UPA.jpg","info":"","text":"4 червня 2014 відкрився третій фітнес-клуб Sport Life у Львові. Клуб знаходиться в БЦ «Технопарк».Мережа «Спорт Лайф» на сьогоднішній день є найбільшою і динамічно зростаючої мережею фітнес клубів в Україні. Головною особливістю і перевагою в принципі роботи мережі є те, що ми пропонуємо найширший спектр фітнес напрямків і послуг, що надається за єдиною мережевою клубною карткою під керівництвом кращих спортивних тренерів. А Клуби мережі «Спорт Лайф» територіально розташовані таким чином, що клієнт завжди може вибирати для відвідування той клуб, який знаходиться ближче до місця його роботи або проживання. При цьому клієнт мережі завжди може отримувати різні унікальні послуги, що надаються тільки в якомусь конкретному клубі, і, при цьому, мати можливість в будь-який час відвідувати кілька або всі клуби мережі!",
         "phone":"+380322201422","site":"http://www.sportlife.ua/","price":"","mon":"","tue":"","wed":"","thu":"","fri":"","sat":"","sun":"",
         "type1":"no","type2":"no","type3":"no","type4":"no","type5":"no"
        }
    ]
}